<?xml version="1.0" encoding="UTF-8"?>
<Root version="1">
	<Application>
		<Name>${com.wowza.wms.context.Application}</Name>
		<AppType>Live</AppType>
		<Description>Simple live application config for Wrench example</Description>
		<Connections>
			<AutoAccept>true</AutoAccept>
			<AllowDomains></AllowDomains>
		</Connections>
		<Streams>
			<StreamType>live</StreamType>
			<StorageDir>${com.wowza.wms.context.VHostConfigHome}/content</StorageDir>
			<KeyDir>${com.wowza.wms.context.VHostConfigHome}/keys</KeyDir>
			<!-- LiveStreamPacketizers (separate with commas): cupertinostreamingpacketizer, smoothstreamingpacketizer, sanjosestreamingpacketizer, mpegdashstreamingpacketizer, cupertinostreamingrepeater, smoothstreamingrepeater, sanjosestreamingrepeater, mpegdashstreamingrepeater -->
			<LiveStreamPacketizers>cupertinostreamingpacketizer,smoothstreamingpacketizer,sanjosestreamingpacketizer,mpegdashstreamingpacketizer</LiveStreamPacketizers>
			<!-- Properties defined here will override any properties defined in conf/Streams.xml for any streams types loaded by this application -->
			<Properties>
			</Properties>
		</Streams>
		<Transcoder>
			<LiveStreamTranscoder>transcoder</LiveStreamTranscoder>
			<Templates>${SourceStreamName}.xml,transrate.xml</Templates>
			<ProfileDir>${com.wowza.wms.context.VHostConfigHome}/transcoder/profiles</ProfileDir>
			<TemplateDir>${com.wowza.wms.context.VHostConfigHome}/transcoder/templates</TemplateDir>
			<Properties>
			</Properties>
		</Transcoder>
		<DVR>
			<Recorders></Recorders>
			<Store></Store>
			<WindowDuration>0</WindowDuration>
			<StorageDir>${com.wowza.wms.context.VHostConfigHome}/dvr</StorageDir>
			<ArchiveStrategy>append</ArchiveStrategy>
			<Properties>
			</Properties>
		</DVR>
		<TimedText>
			<!-- VOD caption providers (separate with commas): vodcaptionprovidermp4_3gpp, vodcaptionproviderttml, vodcaptionproviderwebvtt,  vodcaptionprovidersrt, vodcaptionproviderscc -->
			<VODTimedTextProviders>vodcaptionprovidermp4_3gpp</VODTimedTextProviders>
			<Properties>
			</Properties>
		</TimedText>
		<!-- HTTPStreamers (separate with commas): cupertinostreaming, smoothstreaming, sanjosestreaming, mpegdashstreaming, dvrchunkstreaming -->
		<HTTPStreamers>cupertinostreaming,smoothstreaming,sanjosestreaming,mpegdashstreaming</HTTPStreamers>
		<MediaCache>
			<MediaCacheSourceList></MediaCacheSourceList>
		</MediaCache>
		<SharedObjects>
			<StorageDir>${com.wowza.wms.context.VHostConfigHome}/applications/${com.wowza.wms.context.Application}/sharedobjects/${com.wowza.wms.context.ApplicationInstance}</StorageDir>
		</SharedObjects>
		<Client>
			<IdleFrequency>-1</IdleFrequency>
			<Access>
				<StreamReadAccess>*</StreamReadAccess>
				<StreamWriteAccess>*</StreamWriteAccess>
				<StreamAudioSampleAccess></StreamAudioSampleAccess>
				<StreamVideoSampleAccess></StreamVideoSampleAccess>
				<SharedObjectReadAccess>*</SharedObjectReadAccess>
				<SharedObjectWriteAccess>*</SharedObjectWriteAccess>
			</Access>
		</Client>
		<RTP>
			<!-- RTP/Authentication/[type]Methods defined in Authentication.xml. Default setup includes; none, basic, digest -->
			<Authentication>
				<PublishMethod>none</PublishMethod>
				<PlayMethod>none</PlayMethod>
			</Authentication>
			<!-- RTP/AVSyncMethod. Valid values are: senderreport, systemclock, rtptimecode -->
			<AVSyncMethod>senderreport</AVSyncMethod>
			<MaxRTCPWaitTime>12000</MaxRTCPWaitTime>
			<IdleFrequency>75</IdleFrequency>
			<RTSPSessionTimeout>90000</RTSPSessionTimeout>
			<RTSPMaximumPendingWriteBytes>0</RTSPMaximumPendingWriteBytes>
			<RTSPBindIpAddress></RTSPBindIpAddress>
			<RTSPConnectionIpAddress>0.0.0.0</RTSPConnectionIpAddress>
			<RTSPOriginIpAddress>127.0.0.1</RTSPOriginIpAddress>
			<IncomingDatagramPortRanges>*</IncomingDatagramPortRanges>
			<!-- Properties defined here will override any properties defined in conf/RTP.xml for any depacketizers loaded by this application -->
			<Properties>
			</Properties>
		</RTP>
		<MediaCaster>
			<RTP>
				<RTSP>
					<!-- udp, interleave -->
					<RTPTransportMode>interleave</RTPTransportMode>
				</RTSP>
			</RTP>
			<StreamValidator>
				<Enable>true</Enable>
				<ResetNameGroups>true</ResetNameGroups>
				<StreamStartTimeout>20000</StreamStartTimeout>
				<StreamTimeout>12000</StreamTimeout>
				<VideoStartTimeout>0</VideoStartTimeout>
				<VideoTimeout>0</VideoTimeout>
				<AudioStartTimeout>0</AudioStartTimeout>
				<AudioTimeout>0</AudioTimeout>
				<VideoTCToleranceEnable>false</VideoTCToleranceEnable>
				<VideoTCPosTolerance>3000</VideoTCPosTolerance>
				<VideoTCNegTolerance>-500</VideoTCNegTolerance>
				<AudioTCToleranceEnable>false</AudioTCToleranceEnable>
				<AudioTCPosTolerance>3000</AudioTCPosTolerance>
				<AudioTCNegTolerance>-500</AudioTCNegTolerance>
				<DataTCToleranceEnable>false</DataTCToleranceEnable>
				<DataTCPosTolerance>3000</DataTCPosTolerance>
				<DataTCNegTolerance>-500</DataTCNegTolerance>
				<AVSyncToleranceEnable>false</AVSyncToleranceEnable>
				<AVSyncTolerance>1500</AVSyncTolerance>
				<DebugLog>false</DebugLog>
			</StreamValidator>
			<!-- Properties defined here will override any properties defined in conf/MediaCasters.xml for any MediaCasters loaded by this applications -->
			<Properties>
			</Properties>
		</MediaCaster>
		<MediaReader>
			<!-- Properties defined here will override any properties defined in conf/MediaReaders.xml for any MediaReaders loaded by this applications -->
			<Properties>
			</Properties>
		</MediaReader>
		<MediaWriter>
			<!-- Properties defined here will override any properties defined in conf/MediaWriter.xml for any MediaWriter loaded by this applications -->
			<Properties>
			</Properties>
		</MediaWriter>
		<LiveStreamPacketizer>
			<!-- Properties defined here will override any properties defined in conf/LiveStreamPacketizers.xml for any LiveStreamPacketizers loaded by this applications -->
			<Properties>
			</Properties>
		</LiveStreamPacketizer>
		<HTTPStreamer>
			<!-- Properties defined here will override any properties defined in conf/HTTPStreamers.xml for any HTTPStreamer loaded by this applications -->
			<Properties>
			</Properties>
		</HTTPStreamer>
		<Manager>
			<!-- Properties defined are used by the Manager -->
			<Properties>
			</Properties>
		</Manager>
		<Repeater>
			<OriginURL></OriginURL>
			<QueryString><![CDATA[]]></QueryString>
		</Repeater>
		<StreamRecorder>
			<Properties>
			</Properties>
		</StreamRecorder>
		<Modules>
			<Module>
				<Name>base</Name>
				<Description>Base</Description>
				<Class>com.wowza.wms.module.ModuleCore</Class>
			</Module>
			<Module>
				<Name>logging</Name>
				<Description>Client Logging</Description>
				<Class>com.wowza.wms.module.ModuleClientLogging</Class>
			</Module>
			<Module>
				<Name>flvplayback</Name>
				<Description>FLVPlayback</Description>
				<Class>com.wowza.wms.module.ModuleFLVPlayback</Class>
			</Module>
			<Module>
				<Name>Wrench</Name>
				<Description>Wrench provides user authentication to your application</Description>
				<Class>com.wowzatoolbox.Wrench</Class>
			</Module>
		</Modules>
		<!-- Properties defined here will be added to the IApplication.getProperties() and IApplicationInstance.getProperties() collections -->
		<Properties>
			
			<!-- MINIMAL WRENCH SETTINGS FOR WRENCH DB CONNECTION -->
			<Property><Name>wrench.db.driver</Name><Value>com.mysql.jdbc.Driver</Value></Property>
			<Property><Name>wrench.db.url</Name><Value>jdbc:mysql://localhost:3306/wtbexampledb</Value></Property>
			<Property><Name>wrench.db.user</Name><Value>wtbexample</Value></Property>
			<Property><Name>wrench.db.pass</Name><Value>wtbexample123</Value></Property>
			
			<!-- MINIMAL WRENCH SETTINGS FOR USER AUTHENTICATION -->
			<Property><Name>wrench.encoder.token</Name><Value>encodersecret</Value></Property>
			<Property><Name>wrench.token.resolver.sql</Name><Value>select username, encoder from wtb_tokens where token=:hashedtoken</Value></Property>
			
		</Properties>
	</Application>
</Root>
